ntpoffset
