Metadata-Version: 1.1
Name: collectd-ntp
Version: 0.0.4
Summary: NTP offsets plugin for collectd
Home-page: https://github.com/ministryofjustice/collectd-ntp
Author: MOJDS
Author-email: andy.driver@digital.justice.gov.uk
License: LICENSE
Keywords: python,ministryofjustice,collectd,ntp
Platform: UNKNOWN
Classifier: Programming Language :: Python
Classifier: Programming Language :: Python :: 2.7
Classifier: License :: OSI Approved :: MIT License
Classifier: Operating System :: OS Independent
Classifier: Development Status :: 3 - Alpha
Classifier: Environment :: Plugins
Classifier: Intended Audience :: Developers
Classifier: Natural Language :: English
Classifier: Topic :: Internet
Classifier: Topic :: Software Development :: Libraries :: Python Modules
Classifier: Topic :: System :: Monitoring
Classifier: Topic :: System :: Networking :: Monitoring
Classifier: Topic :: System :: Networking :: Time Synchronization
